githubapiclient/__init__.py
githubapiclient/core.py
tests/__init__.py
tests/test_core.py
githubapiclient-0.2.0.dist-info/LICENSE
githubapiclient-0.2.0.dist-info/METADATA
githubapiclient-0.2.0.dist-info/WHEEL
githubapiclient-0.2.0.dist-info/top_level.txt
githubapiclient-0.2.0.dist-info/RECORD
