Metadata-Version: 2.1
Name: githubapiclient
Version: 0.2.0
Summary: A Python library to interact with the GitHub API
Home-page: https://github.com/anomalous254/githubapiclient
Author: Peter Nyando
Author-email: anomalous254@gmail.com
Classifier: Programming Language :: Python :: 3
Classifier: License :: OSI Approved :: MIT License
Classifier: Operating System :: OS Independent
Requires-Python: >=3.7
License-File: LICENSE
Requires-Dist: requests
